synmetrix_python_client/__init__.py
synmetrix_python_client/auth.py
synmetrix_python_client/graphql/accessLists.gql
synmetrix_python_client/graphql/alerts.gql
synmetrix_python_client/graphql/branches.gql
synmetrix_python_client/graphql/createBranch.gql
synmetrix_python_client/graphql/currentUser.gql
synmetrix_python_client/graphql/datasources.gql
synmetrix_python_client/graphql/explorations.gql
synmetrix_python_client/graphql/members.gql
synmetrix_python_client/graphql/queryLogs.gql
synmetrix_python_client/graphql/reports.gql
synmetrix_python_client/graphql/schemas.gql
synmetrix_python_client/graphql/sqlCredentials.gql
synmetrix_python_client/graphql/teams.gql
synmetrix_python_client/graphql/users.gql
synmetrix_python_client/graphql/versionDocs.gql
synmetrix_python_client/graphql/versions.gql
synmetrix_python_client/graphql_client/__init__.py
synmetrix_python_client/graphql_client/access_list.py
synmetrix_python_client/graphql_client/all_access_lists.py
synmetrix_python_client/graphql_client/all_data_schemas.py
synmetrix_python_client/graphql_client/all_data_sources.py
synmetrix_python_client/graphql_client/all_logs.py
synmetrix_python_client/graphql_client/all_schemas.py
synmetrix_python_client/graphql_client/async_base_client.py
synmetrix_python_client/graphql_client/base_model.py
synmetrix_python_client/graphql_client/check_connection.py
synmetrix_python_client/graphql_client/client.py
synmetrix_python_client/graphql_client/create_access_list.py
synmetrix_python_client/graphql_client/create_alert.py
synmetrix_python_client/graphql_client/create_branch.py
synmetrix_python_client/graphql_client/create_data_source.py
synmetrix_python_client/graphql_client/create_exploration.py
synmetrix_python_client/graphql_client/create_report.py
synmetrix_python_client/graphql_client/create_team.py
synmetrix_python_client/graphql_client/create_version.py
synmetrix_python_client/graphql_client/credentials.py
synmetrix_python_client/graphql_client/current_data_source.py
synmetrix_python_client-0.1.5.dist-info/LICENSE.md
synmetrix_python_client-0.1.5.dist-info/METADATA
synmetrix_python_client-0.1.5.dist-info/WHEEL
synmetrix_python_client-0.1.5.dist-info/entry_points.txt
synmetrix_python_client-0.1.5.dist-info/RECORD
