Metadata-Version: 2.1
Name: synmetrix-python-client
Version: 0.1.5
Summary: A Python client library for interacting with the Synmetrix API
License: MIT
Author: Synmetrix
Author-email: hello@synmetrix.org
Requires-Python: >=3.9, !=2.7.*, !=3.0.*, !=3.1.*, !=3.2.*, !=3.3.*, !=3.4.*, !=3.5.*, !=3.6.*, !=3.7.*, !=3.8.*
Classifier: License :: OSI Approved :: MIT License
Classifier: Programming Language :: Python :: 3
Classifier: Programming Language :: Python :: 3.9
Classifier: Programming Language :: Python :: 3.10
Classifier: Programming Language :: Python :: 3.11
Requires-Dist: PyJWT (==2.10.0)
Requires-Dist: httpx (==0.27.2)
Requires-Dist: pydantic (==2.9.2)
Requires-Dist: python-dotenv (>=1.0.0,<2.0.0)
